{"is_source_file": false, "format": "", "description": "", "external_files": [], "external_methods": [], "published": [], "classes": [], "methods": [], "calls": [], "search-terms": [], "state": 2, "file_id": 8, "knowledge_revision": 57, "git_revision": "c1c7414d0f148da802a8c02d4052b08b9e4f016c", "hash": "2fa61a441770f6c7e2b54d808e4abd9c", "format-version": 4, "code-base-name": "food_website_frontend", "filename": "food_website_frontend/src/routes/styles.css", "revision_history": [{"57": "c1c7414d0f148da802a8c02d4052b08b9e4f016c"}]}